nonebot_plugin_biliforward/__init__.py
nonebot_plugin_biliforward/actcode.py
nonebot_plugin_biliforward/biliapi.py
nonebot_plugin_biliforward/config.py
nonebot_plugin_biliforward/db.py
nonebot_plugin_biliforward/migrations/6ecf6db6302d_first_revision.py
nonebot_plugin_biliforward/model.py
nonebot_plugin_biliforward/qrcodestatus.py
nonebot_plugin_biliforward/rawmsg.py
nonebot_plugin_biliforward-0.1.2.dist-info/LICENSE
nonebot_plugin_biliforward-0.1.2.dist-info/METADATA
nonebot_plugin_biliforward-0.1.2.dist-info/WHEEL
nonebot_plugin_biliforward-0.1.2.dist-info/RECORD
