Metadata-Version: 2.1
Name: nonebot-plugin-biliforward
Version: 0.1.2
Summary: 
License: MIT
Author: Irelia
Author-email: 1074822720@qq.com
Requires-Python: >=3.10,<4.0
Classifier: License :: OSI Approved :: MIT License
Classifier: Programming Language :: Python :: 3
Classifier: Programming Language :: Python :: 3.10
Classifier: Programming Language :: Python :: 3.11
Classifier: Programming Language :: Python :: 3.12
Requires-Dist: aiofiles (>=23.2.1,<24.0.0)
Requires-Dist: httpx (>=0.27.0,<0.28.0)
Requires-Dist: nonebot-adapter-onebot (>=2.4.3,<3.0.0)
Requires-Dist: nonebot-plugin-apscheduler (>=0.4.0,<0.5.0)
Requires-Dist: nonebot-plugin-localstore (>=0.6.0,<0.7.0)
Requires-Dist: nonebot-plugin-orm (>=0.7.3,<0.8.0)
Requires-Dist: nonebot-plugin-send-anything-anywhere (>=0.6.1,<0.7.0)
Requires-Dist: nonebot2 (>=2.3.1,<3.0.0)
Requires-Dist: qrcode (>=7.4.2,<8.0.0)
Requires-Dist: sqlalchemy (>=2.0.31,<3.0.0)
